avapi/__init__.py
avapi/data.py
avapi-0.1.6.dist-info/LICENSE
avapi-0.1.6.dist-info/METADATA
avapi-0.1.6.dist-info/WHEEL
avapi-0.1.6.dist-info/top_level.txt
avapi-0.1.6.dist-info/RECORD
