Metadata-Version: 2.1
Name: avapi
Version: 0.1.6
Summary: Get data from Alpha Vantage into python.
Home-page: http://github.com/olemola/vantage
Author: Ole Olaussen, Xuan Ling
Author-email: ole.olaussen@ekkobit.com, xuan.ling@ekkobit.com
License: MIT
Platform: UNKNOWN
Classifier: Development Status :: 3 - Alpha
Classifier: License :: OSI Approved :: MIT License
Classifier: Programming Language :: Python :: 3
Classifier: Topic :: Office/Business :: Financial :: Investment
Requires-Dist: pandas
Requires-Dist: requests
